moonshotai/__init__.py
moonshotai/version.py
moonshotai-0.0.0.dev1.dist-info/LICENSE
moonshotai-0.0.0.dev1.dist-info/METADATA
moonshotai-0.0.0.dev1.dist-info/WHEEL
moonshotai-0.0.0.dev1.dist-info/top_level.txt
moonshotai-0.0.0.dev1.dist-info/RECORD
